[
    {
        "id": "39",
        "name": "Les Kikis",
        "coachTeamPoints": 62,
        "points": 62,
        "tdFor": 36,
        "tdAgainst": 14,
        "netTd": 22,
        "casualtiesFor": 30,
        "casualtiesAgainst": 26,
        "netCasualties": 4,
        "completionsFor": 0,
        "completionsAgainst": 0,
        "netCompletions": 0,
        "foulsFor": 0,
        "foulsAgainst": 0,
        "netFouls": 0,
        "opponentIdArray": [],
        "opponentCoachTeamIdArray": [
            "35",
            "40",
            "45",
            "42",
            "41",
            "37",
            "34",
            "44"
        ],
        "teams": [
            {
                "opponentIdArray": [
                    "381",
                    "379",
                    "399",
                    "395",
                    "383"
                ],
                "coach": "Darktroll",
                "id": "398",
                "points": 23,
                "opponentsPoints": 72,
                "tdFor": 16,
                "tdAgainst": 6,
                "netTd": 10,
                "casualtiesFor": 6,
                "casualtiesAgainst": 11,
                "netCasualties": -5,
                "completionsFor": 0,
                "completionsAgainst": 0,
                "netCompletions": 0,
                "foulsFor": 0,
                "foulsAgainst": 0,
                "netFouls": 0,
                "win": 4,
                "draw": 1,
                "loss": 0
            },
            {
                "opponentIdArray": [
                    "376",
                    "374",
                    "387",
                    "378",
                    "390"
                ],
                "coach": "Knox",
                "id": "396",
                "points": 21,
                "opponentsPoints": 75,
                "tdFor": 7,
                "tdAgainst": 2,
                "netTd": 5,
                "casualtiesFor": 11,
                "casualtiesAgainst": 7,
                "netCasualties": 4,
                "completionsFor": 0,
                "completionsAgainst": 0,
                "netCompletions": 0,
                "foulsFor": 0,
                "foulsAgainst": 0,
                "netFouls": 0,
                "win": 3,
                "draw": 2,
                "loss": 0
            },
            {
                "opponentIdArray": [
                    "375",
                    "376",
                    "385",
                    "373",
                    "395"
                ],
                "coach": "Willmortis",
                "id": "394",
                "points": 18,
                "opponentsPoints": 57,
                "tdFor": 13,
                "tdAgainst": 6,
                "netTd": 7,
                "casualtiesFor": 13,
                "casualtiesAgainst": 8,
                "netCasualties": 5,
                "completionsFor": 0,
                "completionsAgainst": 0,
                "netCompletions": 0,
                "foulsFor": 0,
                "foulsAgainst": 0,
                "netFouls": 0,
                "win": 3,
                "draw": 1,
                "loss": 1
            }
        ],
        "opponentsPoints": 204,
        "libre": 1,
        "opponentCoachTeamPoints": 334,
        "win": 10,
        "draw": 4,
        "loss": 1,
        "coachTeamWin": 5,
        "coachTeamDraw": 0,
        "coachTeamLoss": 0,
        "finale": false
    },
    {
        "id": "41",
        "name": "Oleg en \u251c\u00aequipe de France",
        "coachTeamPoints": 53,
        "points": 53,
        "tdFor": 19,
        "tdAgainst": 12,
        "netTd": 7,
        "casualtiesFor": 30,
        "casualtiesAgainst": 40,
        "netCasualties": -10,
        "completionsFor": 0,
        "completionsAgainst": 0,
        "netCompletions": 0,
        "foulsFor": 0,
        "foulsAgainst": 0,
        "netFouls": 0,
        "opponentIdArray": [],
        "opponentCoachTeamIdArray": [
            "43",
            "42",
            "38",
            "40",
            "44",
            "37",
            "39",
            "34",
            "45"
        ],
        "teams": [
            {
                "opponentIdArray": [
                    "386",
                    "373",
                    "390",
                    "396",
                    "382"
                ],
                "coach": "Justicium",
                "id": "378",
                "points": 19,
                "opponentsPoints": 68,
                "tdFor": 8,
                "tdAgainst": 3,
                "netTd": 5,
                "casualtiesFor": 11,
                "casualtiesAgainst": 8,
                "netCasualties": 3,
                "completionsFor": 0,
                "completionsAgainst": 0,
                "netCompletions": 0,
                "foulsFor": 0,
                "foulsAgainst": 0,
                "netFouls": 0,
                "win": 3,
                "draw": 1,
                "loss": 1
            },
            {
                "opponentIdArray": [
                    "393",
                    "363",
                    "396",
                    "386",
                    "370"
                ],
                "coach": "Oleg",
                "id": "387",
                "points": 17,
                "opponentsPoints": 66,
                "tdFor": 5,
                "tdAgainst": 4,
                "netTd": 1,
                "casualtiesFor": 13,
                "casualtiesAgainst": 20,
                "netCasualties": -7,
                "completionsFor": 0,
                "completionsAgainst": 0,
                "netCompletions": 0,
                "foulsFor": 0,
                "foulsAgainst": 0,
                "netFouls": 0,
                "win": 2,
                "draw": 2,
                "loss": 1
            },
            {
                "opponentIdArray": [
                    "380",
                    "395",
                    "370",
                    "363",
                    "368"
                ],
                "coach": "Karaak",
                "id": "364",
                "points": 17,
                "opponentsPoints": 59,
                "tdFor": 6,
                "tdAgainst": 5,
                "netTd": 1,
                "casualtiesFor": 6,
                "casualtiesAgainst": 12,
                "netCasualties": -6,
                "completionsFor": 0,
                "completionsAgainst": 0,
                "netCompletions": 0,
                "foulsFor": 0,
                "foulsAgainst": 0,
                "netFouls": 0,
                "win": 2,
                "draw": 2,
                "loss": 1
            }
        ],
        "opponentsPoints": 193,
        "libre": 1,
        "opponentCoachTeamPoints": 381,
        "win": 7,
        "draw": 5,
        "loss": 3,
        "coachTeamWin": 4,
        "coachTeamDraw": 0,
        "coachTeamLoss": 1,
        "finale": false
    },
    {
        "id": "37",
        "name": "EBS",
        "coachTeamPoints": 50,
        "points": 50,
        "tdFor": 26,
        "tdAgainst": 19,
        "netTd": 7,
        "casualtiesFor": 36,
        "casualtiesAgainst": 18,
        "netCasualties": 18,
        "completionsFor": 0,
        "completionsAgainst": 0,
        "netCompletions": 0,
        "foulsFor": 0,
        "foulsAgainst": 0,
        "netFouls": 0,
        "opponentIdArray": [],
        "opponentCoachTeamIdArray": [
            "34",
            "38",
            "35",
            "44",
            "39",
            "41",
            "40",
            "36",
            "43"
        ],
        "teams": [
            {
                "opponentIdArray": [
                    "384",
                    "371",
                    "398",
                    "367",
                    "393"
                ],
                "coach": "Buck\u0027s",
                "id": "399",
                "points": 19,
                "opponentsPoints": 79,
                "tdFor": 10,
                "tdAgainst": 4,
                "netTd": 6,
                "casualtiesFor": 13,
                "casualtiesAgainst": 5,
                "netCasualties": 8,
                "completionsFor": 0,
                "completionsAgainst": 0,
                "netCompletions": 0,
                "foulsFor": 0,
                "foulsAgainst": 0,
                "netFouls": 0,
                "win": 3,
                "draw": 1,
                "loss": 1
            },
            {
                "opponentIdArray": [
                    "382",
                    "375",
                    "364",
                    "383",
                    "387"
                ],
                "coach": "Lord M",
                "id": "370",
                "points": 17,
                "opponentsPoints": 66,
                "tdFor": 5,
                "tdAgainst": 3,
                "netTd": 2,
                "casualtiesFor": 15,
                "casualtiesAgainst": 6,
                "netCasualties": 9,
                "completionsFor": 0,
                "completionsAgainst": 0,
                "netCompletions": 0,
                "foulsFor": 0,
                "foulsAgainst": 0,
                "netFouls": 0,
                "win": 2,
                "draw": 2,
                "loss": 1
            },
            {
                "opponentIdArray": [
                    "383",
                    "389",
                    "365",
                    "393",
                    "380"
                ],
                "coach": "Drix",
                "id": "377",
                "points": 14,
                "opponentsPoints": 52,
                "tdFor": 11,
                "tdAgainst": 12,
                "netTd": -1,
                "casualtiesFor": 8,
                "casualtiesAgainst": 7,
                "netCasualties": 1,
                "completionsFor": 0,
                "completionsAgainst": 0,
                "netCompletions": 0,
                "foulsFor": 0,
                "foulsAgainst": 0,
                "netFouls": 0,
                "win": 2,
                "draw": 1,
                "loss": 2
            }
        ],
        "opponentsPoints": 197,
        "libre": 1,
        "opponentCoachTeamPoints": 383,
        "win": 7,
        "draw": 4,
        "loss": 4,
        "coachTeamWin": 3,
        "coachTeamDraw": 1,
        "coachTeamLoss": 1,
        "finale": false
    },
    {
        "id": "36",
        "name": "Gol\u251c\u00aeadores",
        "coachTeamPoints": 48,
        "points": 48,
        "tdFor": 21,
        "tdAgainst": 17,
        "netTd": 4,
        "casualtiesFor": 26,
        "casualtiesAgainst": 27,
        "netCasualties": -1,
        "completionsFor": 0,
        "completionsAgainst": 0,
        "netCompletions": 0,
        "foulsFor": 0,
        "foulsAgainst": 0,
        "netFouls": 0,
        "opponentIdArray": [],
        "opponentCoachTeamIdArray": [
            "40",
            "44",
            "45",
            null,
            "34",
            "43",
            "42",
            "37",
            "35",
            "38"
        ],
        "teams": [
            {
                "opponentIdArray": [
                    "365",
                    "392",
                    "383",
                    "399",
                    "376"
                ],
                "coach": "Tristelune",
                "id": "367",
                "points": 23,
                "opponentsPoints": 67,
                "tdFor": 10,
                "tdAgainst": 4,
                "netTd": 6,
                "casualtiesFor": 10,
                "casualtiesAgainst": 7,
                "netCasualties": 3,
                "completionsFor": 0,
                "completionsAgainst": 0,
                "netCompletions": 0,
                "foulsFor": 0,
                "foulsAgainst": 0,
                "netFouls": 0,
                "win": 4,
                "draw": 1,
                "loss": 0
            },
            {
                "opponentIdArray": [
                    "373",
                    "368",
                    "391",
                    "372",
                    "388"
                ],
                "coach": "Matt_le_Fou",
                "id": "369",
                "points": 13,
                "opponentsPoints": 41,
                "tdFor": 5,
                "tdAgainst": 5,
                "netTd": 0,
                "casualtiesFor": 8,
                "casualtiesAgainst": 8,
                "netCasualties": 0,
                "completionsFor": 0,
                "completionsAgainst": 0,
                "netCompletions": 0,
                "foulsFor": 0,
                "foulsAgainst": 0,
                "netFouls": 0,
                "win": 2,
                "draw": 0,
                "loss": 3
            },
            {
                "opponentIdArray": [
                    "374",
                    "390",
                    "380",
                    "362",
                    "372"
                ],
                "coach": "Oon",
                "id": "397",
                "points": 12,
                "opponentsPoints": 53,
                "tdFor": 6,
                "tdAgainst": 8,
                "netTd": -2,
                "casualtiesFor": 8,
                "casualtiesAgainst": 12,
                "netCasualties": -4,
                "completionsFor": 0,
                "completionsAgainst": 0,
                "netCompletions": 0,
                "foulsFor": 0,
                "foulsAgainst": 0,
                "netFouls": 0,
                "win": 1,
                "draw": 2,
                "loss": 2
            }
        ],
        "opponentsPoints": 161,
        "libre": 1,
        "opponentCoachTeamPoints": 357,
        "win": 7,
        "draw": 3,
        "loss": 5,
        "coachTeamWin": 4,
        "coachTeamDraw": 0,
        "coachTeamLoss": 1,
        "finale": true,
        "special": 2
    },
    {
        "id": "43",
        "name": "Tribute to Mickael Jackson",
        "coachTeamPoints": 46,
        "points": 46,
        "tdFor": 18,
        "tdAgainst": 18,
        "netTd": 0,
        "casualtiesFor": 26,
        "casualtiesAgainst": 24,
        "netCasualties": 2,
        "completionsFor": 0,
        "completionsAgainst": 0,
        "netCompletions": 0,
        "foulsFor": 0,
        "foulsAgainst": 0,
        "netFouls": 0,
        "opponentIdArray": [],
        "opponentCoachTeamIdArray": [
            "41",
            "35",
            "44",
            "34",
            "42",
            "36",
            "37",
            "38",
            null
        ],
        "teams": [
            {
                "opponentIdArray": [
                    "387",
                    "391",
                    "372",
                    "377",
                    "399"
                ],
                "coach": "Bowl_Hunter",
                "id": "393",
                "points": 16,
                "opponentsPoints": 58,
                "tdFor": 9,
                "tdAgainst": 10,
                "netTd": -1,
                "casualtiesFor": 3,
                "casualtiesAgainst": 9,
                "netCasualties": -6,
                "completionsFor": 0,
                "completionsAgainst": 0,
                "netCompletions": 0,
                "foulsFor": 0,
                "foulsAgainst": 0,
                "netFouls": 0,
                "win": 3,
                "draw": 0,
                "loss": 2
            },
            {
                "opponentIdArray": [
                    "364",
                    "381",
                    "397",
                    "371",
                    "377"
                ],
                "coach": "Scampi",
                "id": "380",
                "points": 15,
                "opponentsPoints": 48,
                "tdFor": 5,
                "tdAgainst": 5,
                "netTd": 0,
                "casualtiesFor": 8,
                "casualtiesAgainst": 6,
                "netCasualties": 2,
                "completionsFor": 0,
                "completionsAgainst": 0,
                "netCompletions": 0,
                "foulsFor": 0,
                "foulsAgainst": 0,
                "netFouls": 0,
                "win": 1,
                "draw": 3,
                "loss": 1
            },
            {
                "opponentIdArray": [
                    "378",
                    "382",
                    "381",
                    "387",
                    "392"
                ],
                "coach": "Amaranth",
                "id": "386",
                "points": 15,
                "opponentsPoints": 44,
                "tdFor": 4,
                "tdAgainst": 3,
                "netTd": 1,
                "casualtiesFor": 15,
                "casualtiesAgainst": 9,
                "netCasualties": 6,
                "completionsFor": 0,
                "completionsAgainst": 0,
                "netCompletions": 0,
                "foulsFor": 0,
                "foulsAgainst": 0,
                "netFouls": 0,
                "win": 2,
                "draw": 1,
                "loss": 2
            }
        ],
        "opponentsPoints": 150,
        "libre": 1,
        "opponentCoachTeamPoints": 328,
        "win": 6,
        "draw": 4,
        "loss": 5,
        "coachTeamWin": 3,
        "coachTeamDraw": 0,
        "coachTeamLoss": 2,
        "finale": false
    },
    {
        "id": "35",
        "name": "Les am\u251c\u00aericains",
        "coachTeamPoints": 38,
        "points": 38,
        "tdFor": 19,
        "tdAgainst": 23,
        "netTd": -4,
        "casualtiesFor": 25,
        "casualtiesAgainst": 24,
        "netCasualties": 1,
        "completionsFor": 0,
        "completionsAgainst": 0,
        "netCompletions": 0,
        "foulsFor": 0,
        "foulsAgainst": 0,
        "netFouls": 0,
        "opponentIdArray": [],
        "opponentCoachTeamIdArray": [
            "39",
            "43",
            "37",
            "38",
            "40",
            "45",
            "44",
            "36",
            "42"
        ],
        "teams": [
            {
                "opponentIdArray": [
                    "396",
                    "394",
                    "363",
                    "390",
                    "367"
                ],
                "coach": "Colonel Castor",
                "id": "376",
                "points": 19,
                "opponentsPoints": 78,
                "tdFor": 6,
                "tdAgainst": 3,
                "netTd": 3,
                "casualtiesFor": 14,
                "casualtiesAgainst": 4,
                "netCasualties": 10,
                "completionsFor": 0,
                "completionsAgainst": 0,
                "netCompletions": 0,
                "foulsFor": 0,
                "foulsAgainst": 0,
                "netFouls": 0,
                "win": 3,
                "draw": 1,
                "loss": 1
            },
            {
                "opponentIdArray": [
                    "394",
                    "370",
                    "388",
                    "379",
                    "373"
                ],
                "coach": "Baltus",
                "id": "375",
                "points": 11,
                "opponentsPoints": 55,
                "tdFor": 7,
                "tdAgainst": 10,
                "netTd": -3,
                "casualtiesFor": 7,
                "casualtiesAgainst": 11,
                "netCasualties": -4,
                "completionsFor": 0,
                "completionsAgainst": 0,
                "netCompletions": 0,
                "foulsFor": 0,
                "foulsAgainst": 0,
                "netFouls": 0,
                "win": 1,
                "draw": 2,
                "loss": 2
            },
            {
                "opponentIdArray": [
                    "398",
                    "380",
                    "386",
                    "365",
                    "385"
                ],
                "coach": "Khelby",
                "id": "381",
                "points": 8,
                "opponentsPoints": 59,
                "tdFor": 6,
                "tdAgainst": 10,
                "netTd": -4,
                "casualtiesFor": 4,
                "casualtiesAgainst": 9,
                "netCasualties": -5,
                "completionsFor": 0,
                "completionsAgainst": 0,
                "netCompletions": 0,
                "foulsFor": 0,
                "foulsAgainst": 0,
                "netFouls": 0,
                "win": 0,
                "draw": 2,
                "loss": 3
            }
        ],
        "opponentsPoints": 192,
        "libre": 1,
        "opponentCoachTeamPoints": 382,
        "win": 4,
        "draw": 5,
        "loss": 6,
        "coachTeamWin": 1,
        "coachTeamDraw": 1,
        "coachTeamLoss": 3,
        "finale": true,
        "special": 1
    },
    {
        "id": "34",
        "name": "Libreville_Abdijan",
        "coachTeamPoints": 47,
        "points": 47,
        "tdFor": 21,
        "tdAgainst": 18,
        "netTd": 3,
        "casualtiesFor": 28,
        "casualtiesAgainst": 26,
        "netCasualties": 2,
        "completionsFor": 0,
        "completionsAgainst": 0,
        "netCompletions": 0,
        "foulsFor": 0,
        "foulsAgainst": 0,
        "netFouls": 0,
        "opponentIdArray": [],
        "opponentCoachTeamIdArray": [
            "37",
            "43",
            "45",
            "42",
            "36",
            "40",
            null,
            "39",
            "41"
        ],
        "teams": [
            {
                "opponentIdArray": [
                    "377",
                    "362",
                    "367",
                    "370",
                    "398"
                ],
                "coach": "Longshot",
                "id": "383",
                "points": 19,
                "opponentsPoints": 78,
                "tdFor": 9,
                "tdAgainst": 6,
                "netTd": 3,
                "casualtiesFor": 7,
                "casualtiesAgainst": 9,
                "netCasualties": -2,
                "completionsFor": 0,
                "completionsAgainst": 0,
                "netCompletions": 0,
                "foulsFor": 0,
                "foulsAgainst": 0,
                "netFouls": 0,
                "win": 3,
                "draw": 1,
                "loss": 1
            },
            {
                "opponentIdArray": [
                    "370",
                    "386",
                    "362",
                    "368",
                    "378"
                ],
                "coach": "Martoni",
                "id": "382",
                "points": 14,
                "opponentsPoints": 64,
                "tdFor": 4,
                "tdAgainst": 5,
                "netTd": -1,
                "casualtiesFor": 9,
                "casualtiesAgainst": 11,
                "netCasualties": -2,
                "completionsFor": 0,
                "completionsAgainst": 0,
                "netCompletions": 0,
                "foulsFor": 0,
                "foulsAgainst": 0,
                "netFouls": 0,
                "win": 1,
                "draw": 3,
                "loss": 1
            },
            {
                "opponentIdArray": [
                    "399",
                    "385",
                    "374",
                    "392",
                    "379"
                ],
                "coach": "Fondu77",
                "id": "384",
                "points": 14,
                "opponentsPoints": 45,
                "tdFor": 8,
                "tdAgainst": 7,
                "netTd": 1,
                "casualtiesFor": 12,
                "casualtiesAgainst": 6,
                "netCasualties": 6,
                "completionsFor": 0,
                "completionsAgainst": 0,
                "netCompletions": 0,
                "foulsFor": 0,
                "foulsAgainst": 0,
                "netFouls": 0,
                "win": 2,
                "draw": 1,
                "loss": 2
            }
        ],
        "opponentsPoints": 187,
        "libre": 1,
        "opponentCoachTeamPoints": 384,
        "win": 6,
        "draw": 5,
        "loss": 4,
        "coachTeamWin": 3,
        "coachTeamDraw": 1,
        "coachTeamLoss": 1,
        "finale": false
    },
    {
        "id": "45",
        "name": "Old Socks\u0027",
        "coachTeamPoints": 46,
        "points": 46,
        "tdFor": 18,
        "tdAgainst": 18,
        "netTd": 0,
        "casualtiesFor": 23,
        "casualtiesAgainst": 17,
        "netCasualties": 6,
        "completionsFor": 0,
        "completionsAgainst": 0,
        "netCompletions": 0,
        "foulsFor": 0,
        "foulsAgainst": 0,
        "netFouls": 0,
        "opponentIdArray": [],
        "opponentCoachTeamIdArray": [
            "44",
            "36",
            "39",
            "34",
            null,
            "40",
            "35",
            "41"
        ],
        "teams": [
            {
                "opponentIdArray": [
                    "391",
                    "398",
                    "373",
                    "375",
                    "384"
                ],
                "coach": "Dipsy",
                "id": "379",
                "points": 18,
                "opponentsPoints": 53,
                "tdFor": 9,
                "tdAgainst": 9,
                "netTd": 0,
                "casualtiesFor": 8,
                "casualtiesAgainst": 8,
                "netCasualties": 0,
                "completionsFor": 0,
                "completionsAgainst": 0,
                "netCompletions": 0,
                "foulsFor": 0,
                "foulsAgainst": 0,
                "netFouls": 0,
                "win": 3,
                "draw": 1,
                "loss": 1
            },
            {
                "opponentIdArray": [
                    "390",
                    "369",
                    "392",
                    "382",
                    "364"
                ],
                "coach": "Acid",
                "id": "368",
                "points": 17,
                "opponentsPoints": 47,
                "tdFor": 5,
                "tdAgainst": 4,
                "netTd": 1,
                "casualtiesFor": 10,
                "casualtiesAgainst": 2,
                "netCasualties": 8,
                "completionsFor": 0,
                "completionsAgainst": 0,
                "netCompletions": 0,
                "foulsFor": 0,
                "foulsAgainst": 0,
                "netFouls": 0,
                "win": 2,
                "draw": 2,
                "loss": 1
            },
            {
                "opponentIdArray": [
                    "389",
                    "383",
                    "382",
                    "397",
                    "374"
                ],
                "coach": "Claudius",
                "id": "362",
                "points": 11,
                "opponentsPoints": 39,
                "tdFor": 4,
                "tdAgainst": 5,
                "netTd": -1,
                "casualtiesFor": 5,
                "casualtiesAgainst": 7,
                "netCasualties": -2,
                "completionsFor": 0,
                "completionsAgainst": 0,
                "netCompletions": 0,
                "foulsFor": 0,
                "foulsAgainst": 0,
                "netFouls": 0,
                "win": 1,
                "draw": 1,
                "loss": 3
            }
        ],
        "opponentsPoints": 139,
        "libre": 1,
        "opponentCoachTeamPoints": 307,
        "win": 6,
        "draw": 4,
        "loss": 5,
        "coachTeamWin": 3,
        "coachTeamDraw": 1,
        "coachTeamLoss": 1,
        "finale": false
    },
    {
        "id": "42",
        "name": "Trol\u251c\u00aeadores",
        "coachTeamPoints": 41,
        "points": 41,
        "tdFor": 23,
        "tdAgainst": 28,
        "netTd": -5,
        "casualtiesFor": 20,
        "casualtiesAgainst": 22,
        "netCasualties": -2,
        "completionsFor": 0,
        "completionsAgainst": 0,
        "netCompletions": 0,
        "foulsFor": 0,
        "foulsAgainst": 0,
        "netFouls": 0,
        "opponentIdArray": [],
        "opponentCoachTeamIdArray": [
            "38",
            "41",
            "34",
            "43",
            "39",
            "36",
            "44",
            "35"
        ],
        "teams": [
            {
                "opponentIdArray": [
                    "363",
                    "388",
                    "393",
                    "369",
                    "397"
                ],
                "coach": "Vincekiller",
                "id": "372",
                "points": 17,
                "opponentsPoints": 47,
                "tdFor": 9,
                "tdAgainst": 7,
                "netTd": 2,
                "casualtiesFor": 5,
                "casualtiesAgainst": 5,
                "netCasualties": 0,
                "completionsFor": 0,
                "completionsAgainst": 0,
                "netCompletions": 0,
                "foulsFor": 0,
                "foulsAgainst": 0,
                "netFouls": 0,
                "win": 3,
                "draw": 0,
                "loss": 2
            },
            {
                "opponentIdArray": [
                    "388",
                    "364",
                    "371",
                    "398",
                    "394"
                ],
                "coach": "Haktar",
                "id": "395",
                "points": 13,
                "opponentsPoints": 64,
                "tdFor": 5,
                "tdAgainst": 8,
                "netTd": -3,
                "casualtiesFor": 10,
                "casualtiesAgainst": 5,
                "netCasualties": 5,
                "completionsFor": 0,
                "completionsAgainst": 0,
                "netCompletions": 0,
                "foulsFor": 0,
                "foulsAgainst": 0,
                "netFouls": 0,
                "win": 2,
                "draw": 1,
                "loss": 2
            },
            {
                "opponentIdArray": [
                    "371",
                    "384",
                    "394",
                    "389",
                    "381"
                ],
                "coach": "Pink_Charlie",
                "id": "385",
                "points": 11,
                "opponentsPoints": 37,
                "tdFor": 9,
                "tdAgainst": 13,
                "netTd": -4,
                "casualtiesFor": 5,
                "casualtiesAgainst": 12,
                "netCasualties": -7,
                "completionsFor": 0,
                "completionsAgainst": 0,
                "netCompletions": 0,
                "foulsFor": 0,
                "foulsAgainst": 0,
                "netFouls": 0,
                "win": 1,
                "draw": 2,
                "loss": 2
            }
        ],
        "opponentsPoints": 148,
        "libre": 1,
        "opponentCoachTeamPoints": 345,
        "win": 6,
        "draw": 3,
        "loss": 6,
        "coachTeamWin": 2,
        "coachTeamDraw": 1,
        "coachTeamLoss": 2,
        "finale": false
    },
    {
        "id": "40",
        "name": "Claquettes Team",
        "coachTeamPoints": 38,
        "points": 38,
        "tdFor": 20,
        "tdAgainst": 25,
        "netTd": -5,
        "casualtiesFor": 21,
        "casualtiesAgainst": 28,
        "netCasualties": -7,
        "completionsFor": 0,
        "completionsAgainst": 0,
        "netCompletions": 0,
        "foulsFor": 0,
        "foulsAgainst": 0,
        "netFouls": 0,
        "opponentIdArray": [],
        "opponentCoachTeamIdArray": [
            "36",
            "41",
            null,
            "39",
            "45",
            "34",
            "37",
            "35",
            "38"
        ],
        "teams": [
            {
                "opponentIdArray": [
                    "367",
                    "366",
                    "377",
                    "381",
                    "363"
                ],
                "coach": "Jmanu",
                "id": "365",
                "points": 16,
                "opponentsPoints": 44,
                "tdFor": 9,
                "tdAgainst": 7,
                "netTd": 2,
                "casualtiesFor": 7,
                "casualtiesAgainst": 9,
                "netCasualties": -2,
                "completionsFor": 0,
                "completionsAgainst": 0,
                "netCompletions": 0,
                "foulsFor": 0,
                "foulsAgainst": 0,
                "netFouls": 0,
                "win": 3,
                "draw": 0,
                "loss": 2
            },
            {
                "opponentIdArray": [
                    "369",
                    "378",
                    "379",
                    "394",
                    "375"
                ],
                "coach": "LoMas",
                "id": "373",
                "points": 11,
                "opponentsPoints": 62,
                "tdFor": 3,
                "tdAgainst": 8,
                "netTd": -5,
                "casualtiesFor": 7,
                "casualtiesAgainst": 7,
                "netCasualties": 0,
                "completionsFor": 0,
                "completionsAgainst": 0,
                "netCompletions": 0,
                "foulsFor": 0,
                "foulsAgainst": 0,
                "netFouls": 0,
                "win": 1,
                "draw": 2,
                "loss": 2
            },
            {
                "opponentIdArray": [
                    "397",
                    "396",
                    "384",
                    "366",
                    "362"
                ],
                "coach": "T\u251c\u00aeva",
                "id": "374",
                "points": 11,
                "opponentsPoints": 42,
                "tdFor": 8,
                "tdAgainst": 10,
                "netTd": -2,
                "casualtiesFor": 7,
                "casualtiesAgainst": 12,
                "netCasualties": -5,
                "completionsFor": 0,
                "completionsAgainst": 0,
                "netCompletions": 0,
                "foulsFor": 0,
                "foulsAgainst": 0,
                "netFouls": 0,
                "win": 1,
                "draw": 2,
                "loss": 2
            }
        ],
        "opponentsPoints": 148,
        "libre": 1,
        "opponentCoachTeamPoints": 374,
        "win": 5,
        "draw": 4,
        "loss": 6,
        "coachTeamWin": 2,
        "coachTeamDraw": 0,
        "coachTeamLoss": 3,
        "finale": false
    },
    {
        "id": "38",
        "name": "Crom",
        "coachTeamPoints": 30,
        "points": 30,
        "tdFor": 18,
        "tdAgainst": 23,
        "netTd": -5,
        "casualtiesFor": 23,
        "casualtiesAgainst": 28,
        "netCasualties": -5,
        "completionsFor": 0,
        "completionsAgainst": 0,
        "netCompletions": 0,
        "foulsFor": 0,
        "foulsAgainst": 0,
        "netFouls": 0,
        "opponentIdArray": [],
        "opponentCoachTeamIdArray": [
            "42",
            "41",
            "37",
            "35",
            "44",
            "43",
            "36",
            "40"
        ],
        "teams": [
            {
                "opponentIdArray": [
                    "385",
                    "399",
                    "395",
                    "380",
                    "389"
                ],
                "coach": "Speedy",
                "id": "371",
                "points": 12,
                "opponentsPoints": 44,
                "tdFor": 8,
                "tdAgainst": 7,
                "netTd": 1,
                "casualtiesFor": 7,
                "casualtiesAgainst": 7,
                "netCasualties": 0,
                "completionsFor": 0,
                "completionsAgainst": 0,
                "netCompletions": 0,
                "foulsFor": 0,
                "foulsAgainst": 0,
                "netFouls": 0,
                "win": 2,
                "draw": 0,
                "loss": 3
            },
            {
                "opponentIdArray": [
                    "372",
                    "387",
                    "376",
                    "364",
                    "365"
                ],
                "coach": "RedDawn",
                "id": "363",
                "points": 10,
                "opponentsPoints": 67,
                "tdFor": 5,
                "tdAgainst": 8,
                "netTd": -3,
                "casualtiesFor": 9,
                "casualtiesAgainst": 9,
                "netCasualties": 0,
                "completionsFor": 0,
                "completionsAgainst": 0,
                "netCompletions": 0,
                "foulsFor": 0,
                "foulsAgainst": 0,
                "netFouls": 0,
                "win": 1,
                "draw": 1,
                "loss": 3
            },
            {
                "opponentIdArray": [
                    "395",
                    "372",
                    "375",
                    "391",
                    "369"
                ],
                "coach": "SoG",
                "id": "388",
                "points": 8,
                "opponentsPoints": 38,
                "tdFor": 5,
                "tdAgainst": 8,
                "netTd": -3,
                "casualtiesFor": 7,
                "casualtiesAgainst": 12,
                "netCasualties": -5,
                "completionsFor": 0,
                "completionsAgainst": 0,
                "netCompletions": 0,
                "foulsFor": 0,
                "foulsAgainst": 0,
                "netFouls": 0,
                "win": 1,
                "draw": 0,
                "loss": 4
            }
        ],
        "opponentsPoints": 149,
        "libre": 1,
        "opponentCoachTeamPoints": 335,
        "win": 4,
        "draw": 1,
        "loss": 10,
        "coachTeamWin": 1,
        "coachTeamDraw": 0,
        "coachTeamLoss": 4,
        "finale": false
    },
    {
        "id": "44",
        "name": "Touritas",
        "coachTeamPoints": 21,
        "points": 21,
        "tdFor": 13,
        "tdAgainst": 30,
        "netTd": -17,
        "casualtiesFor": 17,
        "casualtiesAgainst": 22,
        "netCasualties": -5,
        "completionsFor": 0,
        "completionsAgainst": 0,
        "netCompletions": 0,
        "foulsFor": 0,
        "foulsAgainst": 0,
        "netFouls": 0,
        "opponentIdArray": [],
        "opponentCoachTeamIdArray": [
            "45",
            "43",
            "36",
            "37",
            "41",
            null,
            "42",
            "38",
            "35",
            "39"
        ],
        "teams": [
            {
                "opponentIdArray": [
                    "368",
                    "397",
                    "378",
                    "376",
                    "396"
                ],
                "coach": "Bozo",
                "id": "390",
                "points": 16,
                "opponentsPoints": 75,
                "tdFor": 5,
                "tdAgainst": 5,
                "netTd": 0,
                "casualtiesFor": 6,
                "casualtiesAgainst": 12,
                "netCasualties": -6,
                "completionsFor": 0,
                "completionsAgainst": 0,
                "netCompletions": 0,
                "foulsFor": 0,
                "foulsAgainst": 0,
                "netFouls": 0,
                "win": 3,
                "draw": 0,
                "loss": 2
            },
            {
                "opponentIdArray": [
                    "379",
                    "393",
                    "369",
                    "388",
                    "366"
                ],
                "coach": "Fizzle",
                "id": "391",
                "points": 4,
                "opponentsPoints": 30,
                "tdFor": 3,
                "tdAgainst": 9,
                "netTd": -6,
                "casualtiesFor": 10,
                "casualtiesAgainst": 5,
                "netCasualties": 5,
                "completionsFor": 0,
                "completionsAgainst": 0,
                "netCompletions": 0,
                "foulsFor": 0,
                "foulsAgainst": 0,
                "netFouls": 0,
                "win": 0,
                "draw": 0,
                "loss": 5
            },
            {
                "opponentIdArray": [
                    "362",
                    "377",
                    "366",
                    "385",
                    "371"
                ],
                "coach": "Heduotys",
                "id": "389",
                "points": 1,
                "opponentsPoints": 23,
                "tdFor": 5,
                "tdAgainst": 16,
                "netTd": -11,
                "casualtiesFor": 1,
                "casualtiesAgainst": 5,
                "netCasualties": -4,
                "completionsFor": 0,
                "completionsAgainst": 0,
                "netCompletions": 0,
                "foulsFor": 0,
                "foulsAgainst": 0,
                "netFouls": 0,
                "win": 0,
                "draw": 0,
                "loss": 5
            }
        ],
        "opponentsPoints": 128,
        "libre": 1,
        "opponentCoachTeamPoints": 414,
        "win": 3,
        "draw": 0,
        "loss": 12,
        "coachTeamWin": 0,
        "coachTeamDraw": 0,
        "coachTeamLoss": 5,
        "finale": false
    }
]